{
    "XRP 07/17/23 18:09:30": {
        "Currency": "XRP",
        "Quantity": 971.856015,
        "Date Acquired": "07/17/23",
        "Date Sold": "04/30/24",
        "Proceeds": 501.26198086035043,
        "Cost Basis": 725.94,
        "Return": -224.67801913964962,
        "Term": "SHORT"
    },
    "XRP 07/17/23 19:22:07": {
        "Currency": "XRP",
        "Quantity": 28.143985000000043,
        "Date Acquired": "07/17/23",
        "Date Sold": "04/30/24",
        "Proceeds": 14.516049139649573,
        "Cost Basis": 20.58168197817173,
        "Return": -6.065632838522157,
        "Term": "SHORT"
    }
}